uni_wue_ml_framework_WS2425_T35/__init__.py
uni_wue_ml_framework_WS2425_T35/evaluation.py
uni_wue_ml_framework_WS2425_T35/model_selection.py
uni_wue_ml_framework_WS2425_T35/preprocessing.py
uni_wue_ml_framework_WS2425_T35/saving.py
uni_wue_ml_framework_WS2425_T35/utils.py
uni_wue_ml_framework_WS2425_T35/visualization.py
uni_wue_ml_framework_WS2425_T35/model/__init__.py
uni_wue_ml_framework_WS2425_T35/model/activation_function.py
uni_wue_ml_framework_WS2425_T35/model/cost_function.py
uni_wue_ml_framework_WS2425_T35/model/derivable_function.py
uni_wue_ml_framework_WS2425_T35/model/layer.py
uni_wue_ml_framework_WS2425_T35/model/neural_network.py
uni_wue_ml_framework_WS2425_T35/model/optimizer.py
uni_wue_ml_framework_ws2425_t35-1.0.0.dist-info/METADATA
uni_wue_ml_framework_ws2425_t35-1.0.0.dist-info/WHEEL
uni_wue_ml_framework_ws2425_t35-1.0.0.dist-info/top_level.txt
uni_wue_ml_framework_ws2425_t35-1.0.0.dist-info/RECORD
