Metadata-Version: 2.4
Name: uni_wue_ml_framework_WS2425_T35
Version: 1.0.0
Summary: A machine learning framework
Author: Josef Lindl, Hank Ke, Paul Deger
Project-URL: Repository, https://gitlab2.informatik.uni-wuerzburg.de/hci/teaching/courses/machine-learning/student-submissions/ws24/Team-35/ml-framework
Classifier: Programming Language :: Python :: 3
Classifier: Operating System :: OS Independent
Classifier: License :: OSI Approved :: MIT License
Requires-Dist: numpy
Requires-Dist: matplotlib
Requires-Dist: pandas
Requires-Dist: seaborn
